sentence_stream/__init__.py
sentence_stream/sentence_stream.py
sentence_stream/util.py
sentence_stream-1.2.0.dist-info/licenses/LICENSE.md
sentence_stream-1.2.0.dist-info/METADATA
sentence_stream-1.2.0.dist-info/WHEEL
sentence_stream-1.2.0.dist-info/top_level.txt
sentence_stream-1.2.0.dist-info/zip-safe
sentence_stream-1.2.0.dist-info/RECORD
